{
  "DemographicProjection": {
    "run_demographic_projection": "true",
    "run_hiv_simulation": "false",
    "use_coarse_stratification": "false",
    "run_child_model": "false",
    "age10_adult": "false",
    "age105_open": "false",
    "run_virgin": "false",
    "run_spectrum_model": "false",
    "run_goals": "false"
  },
  "HivFullAgeStratification": {
    "run_demographic_projection": "true",
    "run_hiv_simulation": "true",
    "use_coarse_stratification": "false",
    "run_child_model": "false",
    "age10_adult": "false",
    "age105_open": "false",
    "run_virgin": "false",    
    "run_spectrum_model": "false",
    "run_goals": "false"
  },
  "HivCoarseAgeStratification": {
    "run_demographic_projection": "true",
    "run_hiv_simulation": "true",
    "use_coarse_stratification": "true",
    "run_child_model": "false",
    "age10_adult": "false",
    "age105_open": "false",
    "run_virgin": "false",
    "run_spectrum_model": "false",
    "run_goals": "false"
  },
  "ChildModel": {
    "run_demographic_projection": "true",
    "run_hiv_simulation": "true",
    "use_coarse_stratification": "false",
    "run_child_model": "true",
    "age10_adult": "false",
    "age105_open": "false",
    "run_virgin": "false",
    "run_spectrum_model": "false",
    "run_goals": "false"
  },
  "CoarseChildModel": {
    "run_demographic_projection": "true",
    "run_hiv_simulation": "true",
    "use_coarse_stratification": "true",
    "run_child_model": "true",
    "age10_adult": "false",
    "age105_open": "false",
    "run_virgin": "false",
    "run_spectrum_model": "false",
    "run_goals": "false"
  },
  "Spectrum": {
    "run_demographic_projection": "true",
    "run_hiv_simulation": "true",
    "use_coarse_stratification": "false",
    "run_child_model": "true",
    "age10_adult": "false",
    "age105_open": "false",
    "run_virgin": "false",
    "run_spectrum_model": "true",
    "run_goals": "false"
  },
  "Goals": {
    "run_demographic_projection": "true",
    "run_hiv_simulation": "true",
    "use_coarse_stratification": "false",
    "run_child_model": "true",
    "age10_adult": "false",
    "age105_open": "false",
    "run_virgin": "false",
    "run_spectrum_model": "true",
    "run_goals": "true"
  },
  "GBD": {
    "run_demographic_projection": "true",
    "run_hiv_simulation": "true",
    "use_coarse_stratification": "false",
    "run_child_model": "true",
    "age10_adult": "true",
    "age105_open": "true",
    "run_virgin": "false",
    "run_spectrum_model": "false",
    "run_goals": "false"
  },
  "GBDvirgin": {
    "run_demographic_projection": "true",
    "run_hiv_simulation": "true",
    "use_coarse_stratification": "false",
    "run_child_model": "true",
    "age10_adult": "true",
    "age105_open": "true",
    "run_virgin": "true",
    "run_spectrum_model": "false",
    "run_goals": "false"
  }
}
